tmidiz/MIDI.py
tmidiz/README.md
tmidiz/TCUPY.py
tmidiz/TMELODIES.py
tmidiz/TMIDIX.py
tmidiz/TPLOTS.py
tmidiz/__init__.py
tmidiz/cli.py
tmidiz/directory_tree.py
tmidiz/haystack_search.py
tmidiz/midi_to_colab_audio.py
tmidiz/sample_midis.py
tmidiz/syllables_search.py
tmidiz/tmidiz.py
tmidiz/wordninja.py
tmidiz/x_transformer_1_23_2.py
tmidiz/x_transformer_2_3_1.py
tmidiz/artwork/Project-Los-Angeles.png
tmidiz/artwork/README.md
tmidiz/artwork/Tegridy-Code-2025.png
tmidiz/artwork/__init__.py
tmidiz/docs/__init__.py
tmidiz/examples/README.md
tmidiz/examples/__init__.py
tmidiz/seed_midis/README.md
tmidiz/seed_midis/__init__.py
tmidiz/seed_midis/tmidiz_mi_seed_1.mid
tmidiz/seed_midis/tmidiz_mi_seed_2.mid
tmidiz/seed_midis/tmidiz_mi_seed_3.mid
tmidiz/seed_midis/tmidiz_mi_seed_4.mid
tmidiz/seed_midis/tmidiz_mi_seed_5.mid
tmidiz/seed_midis/tmidiz_mi_seed_6.mid
tmidiz/seed_midis/tmidiz_piano_seed_1.mid
tmidiz/seed_midis/tmidiz_piano_seed_2.mid
tmidiz/seed_midis/tmidiz_piano_seed_3.mid
tmidiz/seed_midis/tmidiz_piano_seed_4.mid
tmidiz/seed_midis/tmidiz_piano_seed_5.mid
tmidiz/seed_midis/tmidiz_piano_seed_6.mid
tmidiz/seed_midis/tmidiz_seed_lyrics.mid
tmidiz/seed_midis/tmidiz_seed_melody.mid
tmidiz/seed_midis/tmidiz_seed_melody_harmonized.mid
tmidiz/seed_midis/tmidiz_seed_midi.mid
tmidiz-25.5.7.dist-info/licenses/LICENSE
tmidiz-25.5.7.dist-info/METADATA
tmidiz-25.5.7.dist-info/WHEEL
tmidiz-25.5.7.dist-info/entry_points.txt
tmidiz-25.5.7.dist-info/top_level.txt
tmidiz-25.5.7.dist-info/RECORD
