Metadata-Version: 2.4
Name: tmidiz
Version: 25.5.7
Summary: Comprehensive MIDI toolkit for MIR and symbolic music AI applications
Author-email: Alex Lev <alexlev61@proton.me>
Maintainer-email: Alex Lev <alexlev61@proton.me>
License-Expression: Apache-2.0
Project-URL: Homepage, https://github.com/asigalov61/tmidiz
Project-URL: SoundCloud, https://soundcloud.com/aleksandr-sigalov-61/
Project-URL: Examples, https://github.com/asigalov61/tmidiz/tree/main/tmidiz/examples
Project-URL: Documentation, https://github.com/asigalov61/tmidiz/main/tmidiz/docs
Project-URL: Issues, https://github.com/asigalov61/tmidiz/issues
Project-URL: Discussions, https://github.com/asigalov61/tmidiz/discussions
Project-URL: HuggingFace, https://huggingface.co/asigalov61
Keywords: MIDI,music,music ai,AI,MIR,MIDI tools
Classifier: Development Status :: 5 - Production/Stable
Classifier: Intended Audience :: Science/Research
Classifier: Topic :: Multimedia :: Sound/Audio :: MIDI
Classifier: Operating System :: OS Independent
Classifier: Programming Language :: Python :: 3.6
Classifier: Programming Language :: Python :: 3.7
Classifier: Programming Language :: Python :: 3.8
Classifier: Programming Language :: Python :: 3.9
Classifier: Programming Language :: Python :: 3.10
Classifier: Programming Language :: Python :: 3.11
Classifier: Programming Language :: Python :: 3.12
Requires-Python: >=3.6
License-File: LICENSE
Requires-Dist: tqdm
Requires-Dist: ipywidgets
Requires-Dist: matplotlib
Requires-Dist: numpy==1.24.4
Requires-Dist: hf-transfer
Requires-Dist: huggingface_hub
Provides-Extra: cupy
Requires-Dist: cupy-cuda12x; extra == "cupy"
Provides-Extra: xtransformer
Requires-Dist: torch==2.6.0; extra == "xtransformer"
Requires-Dist: einops; extra == "xtransformer"
Requires-Dist: einx; extra == "xtransformer"
Provides-Extra: dev
Requires-Dist: pytest; extra == "dev"
Requires-Dist: pytest-cov; extra == "dev"
Requires-Dist: flake8; extra == "dev"
Requires-Dist: black; extra == "dev"
Requires-Dist: isort; extra == "dev"
Requires-Dist: mypy; extra == "dev"
Provides-Extra: docs
Requires-Dist: pydocs; extra == "docs"
Dynamic: license-file
